idem_posix/conf.py
idem_posix/version.py
idem_posix/exec/cmdmod.py
idem_posix/exec/contracts/cmdmod.py
idem_posix/exec/posix/init.py
idem_posix/grains/posix/init.py
idem_posix/grains/posix/net/dns.py
idem_posix/grains/posix/net/fqdn.py
idem_posix/grains/posix/os/uname.py
idem_posix/grains/posix/proc/group.py
idem_posix/grains/posix/proc/pid.py
idem_posix/grains/posix/proc/user.py
idem_posix/grains/posix/system/console.py
idem_posix/grains/posix/system/init_system.py
idem_posix/grains/posix/system/locale.py
idem_posix/grains/posix/system/machine_id.py
idem_posix/grains/posix/system/shell.py
idem_posix/states/cmdmod.py
idem_posix/states/posix/init.py
idem_posix-5.0.0.dist-info/LICENSE
idem_posix-5.0.0.dist-info/METADATA
idem_posix-5.0.0.dist-info/WHEEL
idem_posix-5.0.0.dist-info/entry_points.txt
idem_posix-5.0.0.dist-info/top_level.txt
idem_posix-5.0.0.dist-info/RECORD
