Metadata-Version: 2.1
Name: idem-posix
Version: 5.0.0
Summary: UNKNOWN
Home-page: UNKNOWN
Author: Tyler Johnson
Author-email: tyjohnson@vmware.com
License: UNKNOWN
Platform: UNKNOWN
Classifier: Environment :: Console
Classifier: Intended Audience :: Developers
Classifier: Intended Audience :: Information Technology
Classifier: Intended Audience :: System Administrators
Classifier: Operating System :: POSIX
Classifier: Programming Language :: Python
Classifier: Programming Language :: Python :: 3.8
Classifier: Programming Language :: Python :: 3.9
Classifier: Programming Language :: Python :: 3.10
Classifier: Programming Language :: Python :: 3.11
Classifier: Development Status :: 5 - Production/Stable
Requires-Python: >=3.8
License-File: LICENSE
Requires-Dist: pop
Requires-Dist: idem (>=23.0.0)
Provides-Extra: full
Requires-Dist: grainsv2 ; extra == 'full'
Requires-Dist: grains-universal (>=2.1) ; extra == 'full'
Requires-Dist: dnspython (>=1.14.0) ; extra == 'full'
Provides-Extra: grains
Requires-Dist: dnspython (>=1.14.0) ; extra == 'grains'
Requires-Dist: grainsv2 ; extra == 'grains'
Requires-Dist: grains-universal (>=2.1) ; extra == 'grains'
